bcdata/__init__.py
bcdata/bc2pg.py
bcdata/bcdc.py
bcdata/cli.py
bcdata/database.py
bcdata/wfs.py
bcdata-0.16.0.post1.dist-info/licenses/LICENSE.txt
bcdata-0.16.0.post1.dist-info/METADATA
bcdata-0.16.0.post1.dist-info/WHEEL
bcdata-0.16.0.post1.dist-info/entry_points.txt
bcdata-0.16.0.post1.dist-info/top_level.txt
bcdata-0.16.0.post1.dist-info/RECORD
