Metadata-Version: 2.4
Name: bcdata
Version: 0.16.0.post1
Summary: Download open data, monitor and report on changes
Author-email: Simon Norris <snorris@hillcrestgeo.ca>
Project-URL: Homepage, https://github.com/smnorris/bcdata
Project-URL: Issues, https://github.com/smnorris/bcdata
Classifier: Development Status :: 4 - Beta
Classifier: Programming Language :: Python :: 3.9
Classifier: Programming Language :: Python :: 3.10
Classifier: Programming Language :: Python :: 3.11
Classifier: Programming Language :: Python :: 3.12
Classifier: Programming Language :: Python :: 3.13
Classifier: License :: OSI Approved :: Apache Software License
Classifier: Topic :: Scientific/Engineering :: GIS
Classifier: Operating System :: OS Independent
Requires-Python: >=3.9
License-File: LICENSE.txt
Requires-Dist: geoalchemy2
Requires-Dist: geopandas
Requires-Dist: owslib
Requires-Dist: psycopg2-binary
Requires-Dist: rasterio
Requires-Dist: requests
Requires-Dist: sqlalchemy
Requires-Dist: stamina
Provides-Extra: test
Requires-Dist: pytest; extra == "test"
Requires-Dist: pre-commit; extra == "test"
Requires-Dist: requests-mock; extra == "test"
Dynamic: license-file
